CHANGES.txt
COPYRIGHT.txt
LICENSE.txt
README.txt
ez_setup.py
setup.cfg
setup.py
docs/Makefile
docs/conf.py
docs/glossary.rst
docs/index.rst
docs/.static/logo_hi.gif
docs/.static/repoze.css
repoze/__init__.py
repoze.bfg.formish.egg-info/PKG-INFO
repoze.bfg.formish.egg-info/SOURCES.txt
repoze.bfg.formish.egg-info/dependency_links.txt
repoze.bfg.formish.egg-info/entry_points.txt
repoze.bfg.formish.egg-info/namespace_packages.txt
repoze.bfg.formish.egg-info/not-zip-safe
repoze.bfg.formish.egg-info/requires.txt
repoze.bfg.formish.egg-info/top_level.txt
repoze/bfg/__init__.py
repoze/bfg/formish/__init__.py
repoze/bfg/formish/meta.zcml
repoze/bfg/formish/zcml.py
repoze/bfg/formish/templates/zpt/formish/field/main.html
repoze/bfg/formish/templates/zpt/formish/form/fields.html
repoze/bfg/formish/templates/zpt/formish/form/main.html
repoze/bfg/formish/templates/zpt/formish/sequence/main.html
repoze/bfg/formish/templates/zpt/formish/structure/main.html
repoze/bfg/formish/templates/zpt/formish/test/test.html
repoze/bfg/formish/templates/zpt/formish/widgets/Checkbox/widget.html
repoze/bfg/formish/templates/zpt/formish/widgets/CheckboxMultiChoice/readonly.html
repoze/bfg/formish/templates/zpt/formish/widgets/CheckboxMultiChoice/widget.html
repoze/bfg/formish/templates/zpt/formish/widgets/CheckboxMultiChoiceTree/readonly.html
repoze/bfg/formish/templates/zpt/formish/widgets/CheckboxMultiChoiceTree/widget.html
repoze/bfg/formish/templates/zpt/formish/widgets/CheckedInput/readonly.html
repoze/bfg/formish/templates/zpt/formish/widgets/CheckedInput/widget.html
repoze/bfg/formish/templates/zpt/formish/widgets/CheckedPassword/readonly.html
repoze/bfg/formish/templates/zpt/formish/widgets/CheckedPassword/widget.html
repoze/bfg/formish/templates/zpt/formish/widgets/DateParts/readonly.html
repoze/bfg/formish/templates/zpt/formish/widgets/DateParts/widget.html
repoze/bfg/formish/templates/zpt/formish/widgets/FileUpload/widget.html
repoze/bfg/formish/templates/zpt/formish/widgets/Grid/readonly.html
repoze/bfg/formish/templates/zpt/formish/widgets/Grid/widget.html
repoze/bfg/formish/templates/zpt/formish/widgets/Hidden/readonly.html
repoze/bfg/formish/templates/zpt/formish/widgets/Hidden/widget.html
repoze/bfg/formish/templates/zpt/formish/widgets/Input/readonly.html
