Metadata-Version: 1.0
Name: repoze.bfg.formish
Version: 0.3
Summary: Formish bindings and helpers for repoze.bfg
Home-page: http://www.repoze.org
Author: Agendaless Consulting
Author-email: repoze-dev@lists.repoze.org
License: BSD-derived (http://www.repoze.org/LICENSE.txt)
Keywords: web formish formgen bfg
Platform: UNKNOWN
Classifier: Intended Audience :: Developers
Classifier: Programming Language :: Python
Classifier: Topic :: Internet :: WWW/HTTP
Classifier: Topic :: Internet :: WWW/HTTP :: Dynamic Content
